domainize/__init__.py
domainize/resources/public_suffix_list.dat.gz
domainize-1.2.1.dist-info/METADATA
domainize-1.2.1.dist-info/WHEEL
domainize-1.2.1.dist-info/entry_points.txt
domainize-1.2.1.dist-info/RECORD
