Metadata-Version: 2.3
Name: domainize
Version: 1.2.1
Summary: Library for extracting domains.
License: MIT
Author: Data
Author-email: data@camber.io
Requires-Python: >=3.8,<4.0
Classifier: Development Status :: 4 - Beta
Classifier: License :: OSI Approved :: MIT License
Classifier: Programming Language :: Python :: 3
Classifier: Programming Language :: Python :: 3.8
Classifier: Programming Language :: Python :: 3.9
Classifier: Programming Language :: Python :: 3.10
Classifier: Programming Language :: Python :: 3.11
Classifier: Programming Language :: Python :: 3.12
Classifier: Programming Language :: Python :: 3.13
Classifier: Typing :: Typed
Project-URL: Documentation, https://gitlab.com/rocket-boosters/pipper/domainize
Project-URL: Homepage, https://gitlab.com/rocket-boosters/pipper/domainize
Project-URL: Repository, https://gitlab.com/rocket-boosters/pipper/domainize
